rotation_plots3d/__init__.py
rotation_plots3d/errors.py
rotation_plots3d/graph.py
rotation_plots3d-0.0.1.dist-info/licenses/LICENSE
rotation_plots3d-0.0.1.dist-info/METADATA
rotation_plots3d-0.0.1.dist-info/WHEEL
rotation_plots3d-0.0.1.dist-info/top_level.txt
rotation_plots3d-0.0.1.dist-info/RECORD
