Metadata-Version: 2.4
Name: rotation-plots3d
Version: 0.0.1
Summary: A package to process x, y, z, roll, pitch, yaw data.
Author-email: John Glauber <johnbglauber@gmail.com>
Project-URL: Homepage, https://github.com/jglauber/3dplots
Project-URL: Issues, https://github.com/jglauber/3dplots/issues
Classifier: Programming Language :: Python :: 3
Classifier: Operating System :: OS Independent
Requires-Python: >=3.8
License-File: LICENSE
Requires-Dist: contourpy==1.3.2
Requires-Dist: cycler==0.12.1
Requires-Dist: fonttools==4.58.0
Requires-Dist: kiwisolver==1.4.8
Requires-Dist: matplotlib==3.10.3
Requires-Dist: narwhals==1.32.0
Requires-Dist: numpy==2.2.4
Requires-Dist: packaging==24.2
Requires-Dist: pandas==2.2.3
Requires-Dist: pillow==11.2.1
Requires-Dist: plotly==6.0.1
Requires-Dist: pyparsing==3.2.3
Requires-Dist: pypetb==0.5.1
Requires-Dist: python-dateutil==2.9.0.post0
Requires-Dist: pytz==2025.1
Requires-Dist: scipy==1.15.2
Requires-Dist: six==1.17.0
Requires-Dist: tzdata==2025.2
Dynamic: license-file
